devsecops_engine_tools/__init__.py
devsecops_engine_tools/version.py
devsecops_engine_tools/engine_core/__init__.py
devsecops_engine_tools/engine_core/src/__init__.py
devsecops_engine_tools/engine_core/src/applications/__init__.py
devsecops_engine_tools/engine_core/src/applications/runner_engine_core.py
devsecops_engine_tools/engine_core/src/deployment/__init__.py
devsecops_engine_tools/engine_core/src/deployment/infrastructure/__init__.py
devsecops_engine_tools/engine_core/src/domain/__init__.py
devsecops_engine_tools/engine_core/src/domain/model/__init__.py
devsecops_engine_tools/engine_core/src/domain/model/component.py
devsecops_engine_tools/engine_core/src/domain/model/customs_exceptions.py
devsecops_engine_tools/engine_core/src/domain/model/exclusions.py
devsecops_engine_tools/engine_core/src/domain/model/finding.py
devsecops_engine_tools/engine_core/src/domain/model/input_core.py
devsecops_engine_tools/engine_core/src/domain/model/level_compliance.py
devsecops_engine_tools/engine_core/src/domain/model/level_priority.py
devsecops_engine_tools/engine_core/src/domain/model/level_vulnerability.py
devsecops_engine_tools/engine_core/src/domain/model/report.py
devsecops_engine_tools/engine_core/src/domain/model/threshold.py
devsecops_engine_tools/engine_core/src/domain/model/vulnerability_management.py
devsecops_engine_tools/engine_core/src/domain/model/gateway/__init__.py
devsecops_engine_tools/engine_core/src/domain/model/gateway/devops_platform_gateway.py
devsecops_engine_tools/engine_core/src/domain/model/gateway/metrics_manager_gateway.py
devsecops_engine_tools/engine_core/src/domain/model/gateway/printer_table_gateway.py
devsecops_engine_tools/engine_core/src/domain/model/gateway/risk_score_gateway.py
devsecops_engine_tools/engine_core/src/domain/model/gateway/sbom_manager.py
devsecops_engine_tools/engine_core/src/domain/model/gateway/secrets_manager_gateway.py
devsecops_engine_tools/engine_core/src/domain/model/gateway/vulnerability_management_gateway.py
devsecops_engine_tools-1.129.2.dist-info/METADATA
devsecops_engine_tools-1.129.2.dist-info/WHEEL
devsecops_engine_tools-1.129.2.dist-info/entry_points.txt
devsecops_engine_tools-1.129.2.dist-info/top_level.txt
devsecops_engine_tools-1.129.2.dist-info/RECORD
