Metadata-Version: 2.4
Name: devsecops-engine-tools
Version: 1.129.2
Summary: Tool for DevSecOps strategy
Home-page: https://github.com/bancolombia/devsecops-engine-tools
Author: Bancolombia DevSecOps Team
Author-email: devsecops@bancolombia.com.co
Classifier: Programming Language :: Python :: 3
Classifier: License :: OSI Approved :: GNU Affero General Public License v3 or later (AGPLv3+)
Classifier: Operating System :: OS Independent
Requires-Python: >=3.10
Requires-Dist: requests==2.32.5
Requires-Dist: PyYAML==6.0.3
Requires-Dist: pyfiglet==1.0.4
Requires-Dist: prettytable==3.16.0
Requires-Dist: azure-devops==7.1.0b4
Requires-Dist: marshmallow==4.1.2
Requires-Dist: pytz==2025.2
Requires-Dist: python-decouple==3.8
Requires-Dist: requests_toolbelt==1.0.0
Requires-Dist: pexpect==4.9.0
Requires-Dist: PyGithub==2.8.1
Requires-Dist: distro==1.9.0
Requires-Dist: boto3==1.40.70
Requires-Dist: docker==7.1.0
Requires-Dist: setuptools==78.1.1
Requires-Dist: rich==14.1.0
Requires-Dist: cpe==1.3.1
Requires-Dist: packageurl-python==0.13.4
Requires-Dist: ruamel.yaml==0.18.15
Requires-Dist: Authlib==1.6.6
Requires-Dist: PyJWT==2.10.1
Requires-Dist: sympy==1.14.0
Requires-Dist: urllib3==2.6.3
Requires-Dist: holidays==0.81
Requires-Dist: pyarrow==22.0.0
Dynamic: author
Dynamic: author-email
Dynamic: classifier
Dynamic: description
Dynamic: description-content-type
Dynamic: home-page
Dynamic: requires-dist
Dynamic: requires-python
Dynamic: summary
